geomaglib/Leg_SHA_for_import.py
geomaglib/__init__.py
geomaglib/dipole.py
geomaglib/geoid.py
geomaglib/legendre.py
geomaglib/magmath.py
geomaglib/sh_loader.py
geomaglib/sh_vars.py
geomaglib/util.py
geomaglib-1.2.2.dist-info/licenses/LICENSE
geomaglib-1.2.2.dist-info/METADATA
geomaglib-1.2.2.dist-info/WHEEL
geomaglib-1.2.2.dist-info/top_level.txt
geomaglib-1.2.2.dist-info/RECORD
