Metadata-Version: 2.4
Name: geomaglib
Version: 1.2.2
Summary: The core library for building geomag model.
Author-email: Li-Yin Young <liyin.young@noaa.gov>, Collin Kadlecek <collin.kadlecek@noaa.gov>, Nir Boneh <nir.boneh@noaa.gov>, Liam Kilcommons <liam.kilcommons@colorado.edu>
Maintainer-email: Li-Yin Young <liyin.young@noaa.gov>, Collin Kadlecek <collin.kadlecek@noaa.gov>, Nir Boneh <nir.boneh@noaa.gov>, Liam Kilcommons <liam.kilcommons@colorado.edu>
Project-URL: Homepage, https://github.com/CIRES-Geomagnetism/geomaglib
Classifier: Programming Language :: Python :: 3
Classifier: Programming Language :: Python :: 3
Classifier: Programming Language :: Python :: 3.9
Classifier: Programming Language :: Python :: 3.10
Classifier: Programming Language :: Python :: 3.11
Classifier: Programming Language :: Python :: 3.12
Classifier: Programming Language :: Python :: 3.13
Classifier: License :: OSI Approved :: MIT License
Classifier: Operating System :: OS Independent
License-File: LICENSE
Requires-Dist: numpy
Dynamic: license-file
